{"cameraMode":{"drawMode":0,"name":"Shaded","section":"Shading Mode"},"sceneLighting":true,"audioPlay":false,"sceneViewState":{"showFog":true,"showMaterialUpdate":false,"showSkybox":true,"showFlares":true,"showImageEffects":true,"showParticleSystems":true},"in2DMode":false,"pivot":{"x":-5.996356010437012,"y":3.6254403591156008,"z":-11.98713207244873},"rotation":{"x":-0.2762961983680725,"y":-0.597802996635437,"z":0.23055894672870637,"w":-0.7163861989974976},"size":24.944534301757814,"orthographic":false}